nekoton-0.1.23.dist-info/METADATA
nekoton-0.1.23.dist-info/WHEEL
nekoton-0.1.23.dist-info/licenses/LICENSE
nekoton/__init__.py
nekoton/__main__.py
nekoton/contracts/__init__.py
nekoton/contracts/base.py
nekoton/contracts/ever_wallet.py
nekoton/contracts/giver_v1.py
nekoton/contracts/giver_v2.py
nekoton/contracts/highload_wallet_v2.py
nekoton/contracts/walletv3.py
nekoton/generator/__init__.py
nekoton/gql/__init__.py
nekoton/gql/acc.py
nekoton/gql/filters.py
nekoton/gql/msg.py
nekoton/gql/tx.py
nekoton/nekoton.cpython-313-darwin.so
nekoton/nekoton.pyi
nekoton/py.typed
nekoton-0.1.23.dist-info/RECORD
